djene/__init__.py
djene/djene.py
djene/lookups.py
djene/queryset.py
djene-0.0.1.dist-info/LICENSE
djene-0.0.1.dist-info/METADATA
djene-0.0.1.dist-info/WHEEL
djene-0.0.1.dist-info/RECORD
