Metadata-Version: 2.1
Name: djene
Version: 0.0.1
Summary: Djene: Inject a Django Gene Into Your SQLModel
Author: rfzee
Author-email: rfzee@proton.me
Requires-Python: >=3.12,<4.0
Classifier: Programming Language :: Python :: 3
Classifier: Programming Language :: Python :: 3.12
Requires-Dist: fastapi (>=0.111.0,<0.112.0)
Requires-Dist: loguru (>=0.7.2,<0.8.0)
Requires-Dist: pydantic (>=2.7.4,<3.0.0)
Requires-Dist: sqlmodel (>=0.0.18,<0.0.19)
Requires-Dist: starlette (>=0.37.2,<0.38.0)
